Workbook

Sheet Assumptions
A1: assumption_key | B1: category | C1: lens | D1: value_low | E1: value_base | F1: value_high | G1: unit | H1: source_url | I1: source_type | J1: reviewed_at | K1: owner | L1: notes
A2: build_start_date | B2: timeline | C2: all | D2: 45993 | E2: 45993 | F2: 45993 | G2: date | H2: /Users/olubusayoadewale/rentnow/docs/product/BUILD_COST_BASELINE_REPORT_2026-03-21.md | I2: repo_doc | J2: 46102 | K2: Codex | L2: Fixed build start date for the baseline model.
A3: baseline_snapshot_date | B3: timeline | C3: all | D3: 46102 | E3: 46102 | F3: 46102 | G3: date | H3: /Users/olubusayoadewale/rentnow/docs/product/BUILD_COST_BASELINE_REPORT_2026-03-21.md | I3: repo_doc | J3: 46102 | K3: Codex | L3: Snapshot date for the seeded baseline workbook.
A4: person_days_per_week | B4: model | C4: all | D4: 5 | E4: 5 | F4: 5 | G4: days | H4: /Users/olubusayoadewale/rentnow/docs/product/BUILD_COST_VALUATION_METHOD.md | I4: repo_doc | J4: 46102 | K4: Codex | L4: Model converts person-weeks to person-days using a 5 billable day week.
A5: lean_blended_day_rate | B5: rate | C5: lean / low-cost | D5: 285 | E5: 310 | F5: 353 | G5: GBP/day | H5: https://www.morganmckinley.com/uk/salary-guide/technology/contract-salaries | I5: market_anchor | J5: 46102 | K5: Codex | L5: Blended rate tuned to match the documented lean range across 600 to 850 person-days.
A6: mixed_blended_day_rate | B6: rate | C6: realistic mixed-seniority | D6: 535 | E6: 565 | F6: 612 | G6: GBP/day | H6: https://www.contractoruk.com/market_rates | I6: market_anchor | J6: 46102 | K6: Codex | L6: Most believable central lens. Base rate aligns with the ~£410,000 working figure.
A7: agency_blended_day_rate | B7: rate | C7: premium / agency | D7: 867 | E7: 960 | F7: 1118 | G7: GBP/day | H7: https://www.reed.com/tools/technology-salary-guide-2026 | I7: market_anchor | J7: 46102 | K7: Codex | L7: Agency-equivalent blended delivery rate including margin and delivery overhead.
A8: lean_monthly_continuation | B8: continuation | C8: lean / low-cost | D8: 18000 | E8: 24000 | F8: 30000 | G8: GBP/month | H8: /Users/olubusayoadewale/rentnow/docs/product/BUILD_COST_BASELINE_REPORT_2026-03-21.md | I8: repo_doc | J8: 46102 | K8: Codex | L8: Lean retained specialist continuation range.
A9: mixed_monthly_continuation | B9: continuation | C9: realistic mixed-seniority | D9: 35000 | E9: 50000 | F9: 65000 | G9: GBP/month | H9: /Users/olubusayoadewale/rentnow/docs/product/BUILD_COST_BASELINE_REPORT_2026-03-21.md | I9: repo_doc | J9: 46102 | K9: Codex | L9: Product-team continuation range.
A10: agency_monthly_continuation | B10: continuation | C10: premium / agency | D10: 70000 | E10: 105000 | F10: 140000 | G10: GBP/month | H10: /Users/olubusayoadewale/rentnow/docs/product/BUILD_COST_BASELINE_REPORT_2026-03-21.md | I10: repo_doc | J10: 46102 | K10: Codex | L10: Serious agency or retained squad continuation range.
A11: central_working_figure | B11: valuation | C11: realistic mixed-seniority | D11: 410000 | E11: 410000 | F11: 410000 | G11: GBP | H11: /Users/olubusayoadewale/rentnow/docs/product/BUILD_COST_BASELINE_REPORT_2026-03-21.md | I11: repo_doc | J11: 46102 | K11: Codex | L11: Documented central working figure for stakeholder use.
A12: lean_total_range | B12: valuation | C12: lean / low-cost | D12: 170000 | E12: 224750 | F12: 300000 | G12: GBP | H12: /Users/olubusayoadewale/rentnow/docs/product/BUILD_COST_BASELINE_REPORT_2026-03-21.md | I12: repo_doc | J12: 46102 | K12: Codex | L12: Seeded workbook totals should remain inside the documented lean range.
A13: mixed_total_range | B13: valuation | C13: realistic mixed-seniority | D13: 320000 | E13: 410000 | F13: 520000 | G13: GBP | H13: /Users/olubusayoadewale/rentnow/docs/product/BUILD_COST_BASELINE_REPORT_2026-03-21.md | I13: repo_doc | J13: 46102 | K13: Codex | L13: Seeded workbook totals should remain inside the documented mixed range.
A14: agency_total_range | B14: valuation | C14: premium / agency | D14: 520000 | E14: 696000 | F14: 950000 | G14: GBP | H14: /Users/olubusayoadewale/rentnow/docs/product/BUILD_COST_BASELINE_REPORT_2026-03-21.md | I14: repo_doc | J14: 46102 | K14: Codex | L14: Seeded workbook totals should remain inside the documented agency range.

Sheet Baseline Valuation
A1: snapshot_date | B1: build_start_date | C1: build_end_date | D1: workstream | E1: evidence_summary | F1: confidence | G1: person_weeks_low | H1: person_weeks_base | I1: person_weeks_high | J1: lean_cost_low | K1: lean_cost_base | L1: lean_cost_high | M1: mixed_cost_low | N1: mixed_cost_base | O1: mixed_cost_high | P1: agency_cost_low | Q1: agency_cost_base | R1: agency_cost_high | S1: notes
A2: 46102 | B2: 45993 | C2: 46102 | D2: Marketplace, search, discovery, and engagement | E2: Explore, explore-v2, explore-labs, home, rails, saved, collections, trust cues, and conversion analytics. | F2: Medium | G2: 22 | H2: =ROUND(AVERAGE(G2:I2),1) | I2: 30 | J2: =G2*Assumptions!$E$4*Assumptions!$D$5 | K2: =H2*Assumptions!$E$4*Assumptions!$E$5 | L2: =I2*Assumptions!$E$4*Assumptions!$F$5 | M2: =G2*Assumptions!$E$4*Assumptions!$D$6 | N2: =H2*Assumptions!$E$4*Assumptions!$E$6 | O2: =I2*Assumptions!$E$4*Assumptions!$F$6 | P2: =G2*Assumptions!$E$4*Assumptions!$D$7 | Q2: =H2*Assumptions!$E$4*Assumptions!$E$7 | R2: =I2*Assumptions!$E$4*Assumptions!$F$7 | S2: Seeded from the 2026-03-21 baseline report workstream ranges.
A3: 46102 | B3: 45993 | C3: 46102 | D3: Listings, host workflows, listing quality, and media | E3: Listing create/edit/submit, quality guidance, demo controls, image/video delivery, and host properties manager. | F3: High | G3: 18 | H3: =ROUND(AVERAGE(G3:I3),1) | I3: 24 | J3: =G3*Assumptions!$E$4*Assumptions!$D$5 | K3: =H3*Assumptions!$E$4*Assumptions!$E$5 | L3: =I3*Assumptions!$E$4*Assumptions!$F$5 | M3: =G3*Assumptions!$E$4*Assumptions!$D$6 | N3: =H3*Assumptions!$E$4*Assumptions!$E$6 | O3: =I3*Assumptions!$E$4*Assumptions!$F$6 | P3: =G3*Assumptions!$E$4*Assumptions!$D$7 | Q3: =H3*Assumptions!$E$4*Assumptions!$E$7 | R3: =I3*Assumptions!$E$4*Assumptions!$F$7 | S3: Seeded from the 2026-03-21 baseline report workstream ranges.
A4: 46102 | B4: 45993 | C4: 46102 | D4: Property Requests demand workflow | E4: Tenant request creation, responder matching, admin registry, lifecycle management, telemetry, and notifications. | F4: High | G4: 10 | H4: =ROUND(AVERAGE(G4:I4),1) | I4: 14 | J4: =G4*Assumptions!$E$4*Assumptions!$D$5 | K4: =H4*Assumptions!$E$4*Assumptions!$E$5 | L4: =I4*Assumptions!$E$4*Assumptions!$F$5 | M4: =G4*Assumptions!$E$4*Assumptions!$D$6 | N4: =H4*Assumptions!$E$4*Assumptions!$E$6 | O4: =I4*Assumptions!$E$4*Assumptions!$F$6 | P4: =G4*Assumptions!$E$4*Assumptions!$D$7 | Q4: =H4*Assumptions!$E$4*Assumptions!$E$7 | R4: =I4*Assumptions!$E$4*Assumptions!$F$7 | S4: Seeded from the 2026-03-21 baseline report workstream ranges.
A5: 46102 | B5: 45993 | C5: 46102 | D5: Admin tooling, support, analytics, and operator surfaces | E5: Review desk, support inbox, analytics, diagnostics, settings, and operator-facing admin workflows. | F5: High | G5: 18 | H5: =ROUND(AVERAGE(G5:I5),1) | I5: 26 | J5: =G5*Assumptions!$E$4*Assumptions!$D$5 | K5: =H5*Assumptions!$E$4*Assumptions!$E$5 | L5: =I5*Assumptions!$E$4*Assumptions!$F$5 | M5: =G5*Assumptions!$E$4*Assumptions!$D$6 | N5: =H5*Assumptions!$E$4*Assumptions!$E$6 | O5: =I5*Assumptions!$E$4*Assumptions!$F$6 | P5: =G5*Assumptions!$E$4*Assumptions!$D$7 | Q5: =H5*Assumptions!$E$4*Assumptions!$E$7 | R5: =I5*Assumptions!$E$4*Assumptions!$F$7 | S5: Seeded from the 2026-03-21 baseline report workstream ranges.
A6: 46102 | B6: 45993 | C6: 46102 | D6: Billing, payments, monetisation, and cutover preparation | E6: Subscriptions, PAYG lanes, provider routing, reconcile flows, featured payments, and cutover readiness. | F6: High | G6: 14 | H6: =ROUND(AVERAGE(G6:I6),1) | I6: 20 | J6: =G6*Assumptions!$E$4*Assumptions!$D$5 | K6: =H6*Assumptions!$E$4*Assumptions!$E$5 | L6: =I6*Assumptions!$E$4*Assumptions!$F$5 | M6: =G6*Assumptions!$E$4*Assumptions!$D$6 | N6: =H6*Assumptions!$E$4*Assumptions!$E$6 | O6: =I6*Assumptions!$E$4*Assumptions!$F$6 | P6: =G6*Assumptions!$E$4*Assumptions!$D$7 | Q6: =H6*Assumptions!$E$4*Assumptions!$E$7 | R6: =I6*Assumptions!$E$4*Assumptions!$F$7 | S6: Seeded from the 2026-03-21 baseline report workstream ranges.
A7: 46102 | B7: 45993 | C7: 46102 | D7: Shortlets product lane | E7: Shortlet discovery, map/filter UX, bookings, checkout, payments, reminders, trips, and host ops. | F7: Medium | G7: 20 | H7: =ROUND(AVERAGE(G7:I7),1) | I7: 28 | J7: =G7*Assumptions!$E$4*Assumptions!$D$5 | K7: =H7*Assumptions!$E$4*Assumptions!$E$5 | L7: =I7*Assumptions!$E$4*Assumptions!$F$5 | M7: =G7*Assumptions!$E$4*Assumptions!$D$6 | N7: =H7*Assumptions!$E$4*Assumptions!$E$6 | O7: =I7*Assumptions!$E$4*Assumptions!$F$6 | P7: =G7*Assumptions!$E$4*Assumptions!$D$7 | Q7: =H7*Assumptions!$E$4*Assumptions!$E$7 | R7: =I7*Assumptions!$E$4*Assumptions!$F$7 | S7: Seeded from the 2026-03-21 baseline report workstream ranges.
A8: 46102 | B8: 45993 | C8: 46102 | D8: Docs, help, training, and admin runbooks | E8: Role help docs, admin runbooks, audit documents, and update-note discipline. | F8: High | G8: 6 | H8: =ROUND(AVERAGE(G8:I8),1) | I8: 10 | J8: =G8*Assumptions!$E$4*Assumptions!$D$5 | K8: =H8*Assumptions!$E$4*Assumptions!$E$5 | L8: =I8*Assumptions!$E$4*Assumptions!$F$5 | M8: =G8*Assumptions!$E$4*Assumptions!$D$6 | N8: =H8*Assumptions!$E$4*Assumptions!$E$6 | O8: =I8*Assumptions!$E$4*Assumptions!$F$6 | P8: =G8*Assumptions!$E$4*Assumptions!$D$7 | Q8: =H8*Assumptions!$E$4*Assumptions!$E$7 | R8: =I8*Assumptions!$E$4*Assumptions!$F$7 | S8: Seeded from the 2026-03-21 baseline report workstream ranges.
A9: 46102 | B9: 45993 | C9: 46102 | D9: Stability, release gates, PWA, CI, migrations, and automation ops | E9: Go-live stabilization, PWA hardening, CI/release health, migration guards, and automation ops docs. | F9: Medium | G9: 12 | H9: =ROUND(AVERAGE(G9:I9),1) | I9: 18 | J9: =G9*Assumptions!$E$4*Assumptions!$D$5 | K9: =H9*Assumptions!$E$4*Assumptions!$E$5 | L9: =I9*Assumptions!$E$4*Assumptions!$F$5 | M9: =G9*Assumptions!$E$4*Assumptions!$D$6 | N9: =H9*Assumptions!$E$4*Assumptions!$E$6 | O9: =I9*Assumptions!$E$4*Assumptions!$F$6 | P9: =G9*Assumptions!$E$4*Assumptions!$D$7 | Q9: =H9*Assumptions!$E$4*Assumptions!$E$7 | R9: =I9*Assumptions!$E$4*Assumptions!$F$7 | S9: Seeded from the 2026-03-21 baseline report workstream ranges.
D10: Baseline totals | E10: Totals row sums the seeded workstream rows directly above. | G10: =SUM(G2:G9) | H10: =SUM(H2:H9) | I10: =SUM(I2:I9) | J10: =SUM(J2:J9) | K10: =SUM(K2:K9) | L10: =SUM(L2:L9) | M10: =SUM(M2:M9) | N10: =SUM(N2:N9) | ... R10: =SUM(R2:R9) | S10: Central mixed base should sit near the documented ~£410,000 figure.

Sheet Weekly Increments
A1: week_ending | B1: review_window_start | C1: review_window_end | D1: run_id | E1: reviewer | F1: approval_status | G1: changed_files_count | H1: commit_count | I1: update_notes_count | J1: primary_workstream | K1: secondary_workstream | L1: shipped_summary | M1: evidence_refs | N1: effort_person_days_low | O1: effort_person_days_base | P1: effort_person_days_high | Q1: role_mix_applied | R1: lean_add_low | S1: lean_add_base | T1: lean_add_high | U1: mixed_add_low | V1: mixed_add_base | W1: mixed_add_high | X1: agency_add_low | Y1: agency_add_base | Z1: agency_add_high | AA1: confidence | AB1: next_action | AC1: notes
A2: 46109 | B2: 46103 | C2: 46109 | D2: TEMPLATE-REPLACE | E2: Reviewer name | F2: draft | L2: Replace with the approved weekly shipped summary. | M2: 2 to 5 evidence refs | Q2: mixed engineering + QA + docs | R2: =IF(OR($N2="",$F2<>"approved"),"",$N2*Assumptions!$E$5) | S2: =IF(OR($O2="",$F2<>"approved"),"",$O2*Assumptions!$E$5) | T2: =IF(OR($P2="",$F2<>"approved"),"",$P2*Assumptions!$E$5) | U2: =IF(OR($N2="",$F2<>"approved"),"",$N2*Assumptions!$E$6) | V2: =IF(OR($O2="",$F2<>"approved"),"",$O2*Assumptions!$E$6) | W2: =IF(OR($P2="",$F2<>"approved"),"",$P2*Assumptions!$E$6) | X2: =IF(OR($N2="",$F2<>"approved"),"",$N2*Assumptions!$E$7) | Y2: =IF(OR($O2="",$F2<>"approved"),"",$O2*Assumptions!$E$7) | Z2: =IF(OR($P2="",$F2<>"approved"),"",$P2*Assumptions!$E$7) | AA2: Medium | AB2: review required | AC2: Template row; copy down or replace after review.

Sheet Cumulative Totals
A1: Build Cost Ledger v1 - cumulative view
A3: Baseline totals | F3: Central working figure
A4: lens | B4: baseline_low | C4: baseline_base | D4: baseline_high | F4: =Assumptions!E11
A5: lean / low-cost | B5: ='Baseline Valuation'!J10 | C5: ='Baseline Valuation'!K10 | D5: ='Baseline Valuation'!L10
A6: realistic mixed-seniority | B6: ='Baseline Valuation'!M10 | C6: ='Baseline Valuation'!N10 | D6: ='Baseline Valuation'!O10 | F6: Build start date
A7: premium / agency | B7: ='Baseline Valuation'!P10 | C7: ='Baseline Valuation'!Q10 | D7: ='Baseline Valuation'!R10 | F7: =Assumptions!E2
A10: Weekly additions to date
A11: lens | B11: weekly_low_total | C11: weekly_base_total | D11: weekly_high_total
A12: lean / low-cost | B12: =SUMIFS('Weekly Increments'!$R:$R,'Weekly Increments'!$F:$F,"approved") | C12: =SUMIFS('Weekly Increments'!$S:$S,'Weekly Increments'!$F:$F,"approved") | D12: =SUMIFS('Weekly Increments'!$T:$T,'Weekly Increments'!$F:$F,"approved")
A13: realistic mixed-seniority | B13: =SUMIFS('Weekly Increments'!$U:$U,'Weekly Increments'!$F:$F,"approved") | C13: =SUMIFS('Weekly Increments'!$V:$V,'Weekly Increments'!$F:$F,"approved") | D13: =SUMIFS('Weekly Increments'!$W:$W,'Weekly Increments'!$F:$F,"approved")
A14: premium / agency | B14: =SUMIFS('Weekly Increments'!$X:$X,'Weekly Increments'!$F:$F,"approved") | C14: =SUMIFS('Weekly Increments'!$Y:$Y,'Weekly Increments'!$F:$F,"approved") | D14: =SUMIFS('Weekly Increments'!$Z:$Z,'Weekly Increments'!$F:$F,"approved")
A17: Current cumulative estimate
A18: lens | B18: cumulative_low | C18: cumulative_base | D18: cumulative_high
A19: lean / low-cost | B19: =B5+B12 | C19: =C5+C12 | D19: =D5+D12
A20: realistic mixed-seniority | B20: =B6+B13 | C20: =C6+C13 | D20: =D6+D13
A21: premium / agency | B21: =B7+B14 | C21: =C7+C14 | D21: =D7+D14
A24: Monthly continuation assumptions
A25: lens | B25: monthly_continuation_low | C25: monthly_continuation_base | D25: monthly_continuation_high
A26: lean / low-cost | B26: =Assumptions!D8 | C26: =Assumptions!E8 | D26: =Assumptions!F8
A27: realistic mixed-seniority | B27: =Assumptions!D9 | C27: =Assumptions!E9 | D27: =Assumptions!F9
A28: premium / agency | B28: =Assumptions!D10 | C28: =Assumptions!E10 | D28: =Assumptions!F10

Sheet Workstream Log
A1: week_ending | B1: workstream | C1: batch_title | D1: summary | E1: important_files | F1: important_update_notes | G1: impact_level | H1: confidence | I1: reviewer_note
A2: 46102 | B2: Marketplace, search, discovery, and engagement | C2: Baseline valuation snapshot | D2: Explore, explore-v2, explore-labs, home, rails, saved, collections, trust cues, and conversion analytics. | E2: docs/product/BUILD_COST_BASELINE_REPORT_2026-03-21.md; docs/product/ROADMAP.md | F2: web/docs/updates/** (baseline evidence pool) | G2: Baseline | H2: Medium | I2: Seed entry for the starter ledger workbook.
A3: 46102 | B3: Listings, host workflows, listing quality, and media | C3: Baseline valuation snapshot | D3: Listing create/edit/submit, quality guidance, demo controls, image/video delivery, and host properties manager. | E3: docs/product/BUILD_COST_BASELINE_REPORT_2026-03-21.md; docs/product/ROADMAP.md | F3: web/docs/updates/** (baseline evidence pool) | G3: Baseline | H3: High | I3: Seed entry for the starter ledger workbook.
A4: 46102 | B4: Property Requests demand workflow | C4: Baseline valuation snapshot | D4: Tenant request creation, responder matching, admin registry, lifecycle management, telemetry, and notifications. | E4: docs/product/BUILD_COST_BASELINE_REPORT_2026-03-21.md; docs/product/ROADMAP.md | F4: web/docs/updates/** (baseline evidence pool) | G4: Baseline | H4: High | I4: Seed entry for the starter ledger workbook.
A5: 46102 | B5: Admin tooling, support, analytics, and operator surfaces | C5: Baseline valuation snapshot | D5: Review desk, support inbox, analytics, diagnostics, settings, and operator-facing admin workflows. | E5: docs/product/BUILD_COST_BASELINE_REPORT_2026-03-21.md; docs/product/ROADMAP.md | F5: web/docs/updates/** (baseline evidence pool) | G5: Baseline | H5: High | I5: Seed entry for the starter ledger workbook.
A6: 46102 | B6: Billing, payments, monetisation, and cutover preparation | C6: Baseline valuation snapshot | D6: Subscriptions, PAYG lanes, provider routing, reconcile flows, featured payments, and cutover readiness. | E6: docs/product/BUILD_COST_BASELINE_REPORT_2026-03-21.md; docs/product/ROADMAP.md | F6: web/docs/updates/** (baseline evidence pool) | G6: Baseline | H6: High | I6: Seed entry for the starter ledger workbook.
A7: 46102 | B7: Shortlets product lane | C7: Baseline valuation snapshot | D7: Shortlet discovery, map/filter UX, bookings, checkout, payments, reminders, trips, and host ops. | E7: docs/product/BUILD_COST_BASELINE_REPORT_2026-03-21.md; docs/product/ROADMAP.md | F7: web/docs/updates/** (baseline evidence pool) | G7: Baseline | H7: Medium | I7: Seed entry for the starter ledger workbook.
A8: 46102 | B8: Docs, help, training, and admin runbooks | C8: Baseline valuation snapshot | D8: Role help docs, admin runbooks, audit documents, and update-note discipline. | E8: docs/product/BUILD_COST_BASELINE_REPORT_2026-03-21.md; docs/product/ROADMAP.md | F8: web/docs/updates/** (baseline evidence pool) | G8: Baseline | H8: High | I8: Seed entry for the starter ledger workbook.
A9: 46102 | B9: Stability, release gates, PWA, CI, migrations, and automation ops | C9: Baseline valuation snapshot | D9: Go-live stabilization, PWA hardening, CI/release health, migration guards, and automation ops docs. | E9: docs/product/BUILD_COST_BASELINE_REPORT_2026-03-21.md; docs/product/ROADMAP.md | F9: web/docs/updates/** (baseline evidence pool) | G9: Baseline | H9: Medium | I9: Seed entry for the starter ledger workbook.

Sheet Notes & Confidence
A1: Build Cost Ledger v1 notes and operating guidance
A3: This workbook is a build-cost valuation model, not audited spend or business valuation.
A4: This starter workbook uses the six-tab operating layout requested for this batch. README-style usage notes are embedded here instead of a separate README tab.
A5: Weekly increments should stay review-based. Do not silently append approved rows without human review.
A7: date | B7: entry_type | C7: lens | D7: workstream | E7: confidence_change | F7: reason | G7: owner | H7: follow_up
A8: 46102 | B8: model_warning | C8: all | D8: all | E8: n/a | F8: The workbook values estimate reproduction cost from repo truth and should not be presented as cash spent. | G8: Codex | H8: Keep stakeholder summaries explicit about the model limits.
A9: 46102 | B9: baseline_note | C9: realistic mixed-seniority | D9: all | E9: High | F9: Central working figure is about £410,000 and should remain the default stakeholder number unless the method changes. | G9: Codex | H9: Review only if the methodology doc changes.
A10: 46102 | B10: workbook_structure | C10: all | D10: all | E10: Medium | F10: Weekly Increments starts with a draft template row. Approved totals in Cumulative Totals intentionally ignore non-approved rows. | G10: Codex | H10: Copy the template row for each new reviewed week.
